setup.py
simpcfg/__init__.py
simpcfg/config.py
simpcfg/test.py
simpcfg.egg-info/PKG-INFO
simpcfg.egg-info/SOURCES.txt
simpcfg.egg-info/dependency_links.txt
simpcfg.egg-info/requires.txt
simpcfg.egg-info/top_level.txt