Metadata-Version: 2.1
Name: simpcfg
Version: 0.2.0
Summary: Simple Configuration Manager
Home-page: https://github.com/StephenMal/simpcfg
Author: Stephen Maldonado
Author-email: simpcfg@stephenmal.com
License: UNKNOWN
Platform: UNKNOWN
Classifier: Development Status :: 1 - Planning
Classifier: Programming Language :: Python :: 3 :: Only
Classifier: Topic :: Utilities
